argtyp/__init__.py
argtyp/argtyp.py
argtyp-0.0.5.dist-info/DESCRIPTION.rst
argtyp-0.0.5.dist-info/METADATA
argtyp-0.0.5.dist-info/RECORD
argtyp-0.0.5.dist-info/WHEEL
argtyp-0.0.5.dist-info/metadata.json
argtyp-0.0.5.dist-info/top_level.txt
