Metadata-Version: 2.0
Name: argtyp
Version: 0.0.5
Summary: Argument type collection for argparse
Home-page: https://github.com/raviqqe/argtyp/
Author: Yota Toyama
Author-email: raviqqe@gmail.com
License: Public Domain
Platform: UNKNOWN
Classifier: Development Status :: 3 - Alpha
Classifier: Intended Audience :: Developers
Classifier: License :: Public Domain
Classifier: Programming Language :: Python :: 3.5
Classifier: Topic :: Utilities
